{
  "sexual_terms": [
    {
      "term": "محتوى ديال الكبار",
      "weight": 3
    },
    {
      "term": "محتوى جنسي",
      "weight": 3
    },
    {
      "term": "محتوى صريح",
      "weight": 3
    },
    {
      "term": "لقطة حميمة",
      "weight": 3
    },
    {
      "term": "تعرا",
      "weight": 3
    },
    {
      "term": "جسد عريان",
      "weight": 3
    },
    {
      "term": "رغبة جنسية",
      "weight": 3
    },
    {
      "term": "إثارة جنسية",
      "weight": 3
    },
    {
      "term": "علاقة جنسية",
      "weight": 3
    },
    {
      "term": "علاقة حميمة",
      "weight": 3
    },
    {
      "term": "فعل جنسي",
      "weight": 3
    },
    {
      "term": "متعة جنسية",
      "weight": 3
    },
    {
      "term": "نشوة",
      "weight": 3
    },
    {
      "term": "عادة سرية",
      "weight": 3
    },
    {
      "term": "مداعبة",
      "weight": 3
    },
    {
      "term": "إيحاء جنسي",
      "weight": 3
    },
    {
      "term": "تخيلات جنسية",
      "weight": 3
    },
    {
      "term": "رغبة حميمة",
      "weight": 3
    },
    {
      "term": "اقتراح جنسي",
      "weight": 3
    },
    {
      "term": "تلميح جنسي",
      "weight": 3
    },
    {
      "term": "إغراء",
      "weight": 3
    },
    {
      "term": "هضرة شهوانية",
      "weight": 3
    },
    {
      "term": "كلام جنسي",
      "weight": 3
    },
    {
      "term": "حوار جنسي",
      "weight": 3
    },
    {
      "term": "وصف جنسي",
      "weight": 3
    }
  ],
  "explicit_acts": [
    {
      "term": "جماع",
      "weight": 5
    },
    {
      "term": "ممارسة الجنس",
      "weight": 5
    },
    {
      "term": "علاقة فراش",
      "weight": 5
    },
    {
      "term": "جنس فموي",
      "weight": 5
    },
    {
      "term": "جنس شرجي",
      "weight": 5
    },
    {
      "term": "جنس مهبلي",
      "weight": 5
    },
    {
      "term": "وضعية جنسية",
      "weight": 5
    },
    {
      "term": "مداعبة حميمة",
      "weight": 5
    },
    {
      "term": "لمس جنسي",
      "weight": 5
    },
    {
      "term": "تحرش جنسي",
      "weight": 5
    },
    {
      "term": "لقطة فراش",
      "weight": 5
    },
    {
      "term": "علاقة جسدية",
      "weight": 5
    },
    {
      "term": "بوسة سخونة",
      "weight": 5
    },
    {
      "term": "حضن حميم",
      "weight": 5
    },
    {
      "term": "ممارسة حميمة",
      "weight": 5
    },
    {
      "term": "فعل حميم",
      "weight": 5
    },
    {
      "term": "ممارسة جنسية صريحة",
      "weight": 5
    },
    {
      "term": "تمثيل جنسي",
      "weight": 5
    },
    {
      "term": "وصف فعل جنسي",
      "weight": 5
    },
    {
      "term": "مشهد جنسي",
      "weight": 5
    },
    {
      "term": "تصوير جنسي",
      "weight": 5
    },
    {
      "term": "رقص سخون",
      "weight": 5
    },
    {
      "term": "حيد الحوايج",
      "weight": 5
    },
    {
      "term": "تعرا قدام الكاميرا",
      "weight": 5
    },
    {
      "term": "لقطة خاصة",
      "weight": 5
    }
  ],
  "body_terms": [
    {
      "term": "صدر عريان",
      "weight": 4
    },
    {
      "term": "البزولة",
      "weight": 4
    },
    {
      "term": "المؤخرة",
      "weight": 4
    },
    {
      "term": "بلايص حساسة",
      "weight": 4
    },
    {
      "term": "أعضاء تناسلية",
      "weight": 4
    },
    {
      "term": "عضو ذكري",
      "weight": 4
    },
    {
      "term": "عضو أنثوي",
      "weight": 4
    },
    {
      "term": "قضيب",
      "weight": 4
    },
    {
      "term": "مهبل",
      "weight": 4
    },
    {
      "term": "فرج",
      "weight": 4
    },
    {
      "term": "خصيتين",
      "weight": 4
    },
    {
      "term": "شرج",
      "weight": 4
    },
    {
      "term": "بلاصة حميمة",
      "weight": 4
    },
    {
      "term": "حوايج داخلية مثيرة",
      "weight": 4
    },
    {
      "term": "لباس شفاف",
      "weight": 4
    },
    {
      "term": "جسم مكشوف",
      "weight": 4
    },
    {
      "term": "جسم عريان",
      "weight": 4
    },
    {
      "term": "جلد مكشوف",
      "weight": 4
    },
    {
      "term": "وقفة موحية",
      "weight": 4
    },
    {
      "term": "نظرة شهوانية",
      "weight": 4
    },
    {
      "term": "حركات موحية",
      "weight": 4
    },
    {
      "term": "تصرف جنسي",
      "weight": 4
    },
    {
      "term": "لباس فاضح",
      "weight": 4
    },
    {
      "term": "تصويرة حميمة",
      "weight": 4
    },
    {
      "term": "فيديو خاص",
      "weight": 4
    }
  ],
  "solicitation_terms": [
    {
      "term": "لقاء جنسي",
      "weight": 4
    },
    {
      "term": "موعد حميم",
      "weight": 4
    },
    {
      "term": "طلب جنسي",
      "weight": 4
    },
    {
      "term": "خدمة جنسية",
      "weight": 4
    },
    {
      "term": "دعارة",
      "weight": 4
    },
    {
      "term": "إعلان جنسي",
      "weight": 4
    },
    {
      "term": "دردشة إباحية",
      "weight": 4
    },
    {
      "term": "ميساج جنسي",
      "weight": 4
    },
    {
      "term": "تصاور عريانة",
      "weight": 4
    },
    {
      "term": "فيديو حميم",
      "weight": 4
    },
    {
      "term": "عيطة سخونة",
      "weight": 4
    },
    {
      "term": "كاميرا ديال الكبار",
      "weight": 4
    },
    {
      "term": "ويب كام جنسي",
      "weight": 4
    },
    {
      "term": "موقع إباحي",
      "weight": 4
    },
    {
      "term": "فيلم إباحي",
      "weight": 4
    },
    {
      "term": "بورنو",
      "weight": 4
    },
    {
      "term": "تصويرة إباحية",
      "weight": 4
    },
    {
      "term": "فيديو إباحي",
      "weight": 4
    },
    {
      "term": "مشهد إباحي",
      "weight": 4
    },
    {
      "term": "محتوى خادش",
      "weight": 4
    },
    {
      "term": "تصاور خاصة",
      "weight": 4
    },
    {
      "term": "صيفط تصاور حميمة",
      "weight": 4
    },
    {
      "term": "طلب تصاور عريانة",
      "weight": 4
    },
    {
      "term": "تحريض جنسي",
      "weight": 4
    },
    {
      "term": "هضرة ديال الجنس",
      "weight": 4
    }
  ]
}
